marketools/__init__.py
marketools/stock.py
marketools/wallet.py
marketools/analysis/__init__.py
marketools/analysis/heikinashi.py
marketools/analysis/macd.py
marketools/analysis/moving_average.py
marketools/analysis/price.py
marketools/analysis/rsi.py
marketools/analysis/volume.py
marketools/stqscraper/__init__.py
marketools/stqscraper/fundamentals.py
marketools/stqscraper/scrapers.py
marketools/stqscraper/stockquotes.py
marketools-1.0.1.dist-info/LICENSE
marketools-1.0.1.dist-info/METADATA
marketools-1.0.1.dist-info/WHEEL
marketools-1.0.1.dist-info/top_level.txt
marketools-1.0.1.dist-info/RECORD
