Metadata-Version: 2.1
Name: marketools
Version: 1.0.1
Summary: Tools for stock market analysis.
Home-page: https://github.com/AlbertRtk/marketools
Maintainer: Albert Ratajczak
Maintainer-email: ratajczakalbert@gmail.com
License: UNKNOWN
Platform: UNKNOWN
Classifier: Programming Language :: Python :: 3
Classifier: License :: OSI Approved :: BSD License
Classifier: Operating System :: OS Independent
Requires-Python: >=3.8
Requires-Dist: pandas (>=1.1.4)
Requires-Dist: requests (>=2.25.0)
Requires-Dist: numpy (>=1.19.4)
Requires-Dist: lxml (>=4.6.2)
